prov/__init__.py
prov/constants.py
prov/dot.py
prov/graph.py
prov/identifier.py
prov/model.py
prov/serializers/__init__.py
prov/serializers/provjson.py
prov/serializers/provn.py
prov/serializers/provrdf.py
prov/serializers/provxml.py
prov/tests/__init__.py
prov/tests/attributes.py
prov/tests/examples.py
prov/tests/qnames.py
prov/tests/statements.py
prov/tests/test_dot.py
prov/tests/test_extras.py
prov/tests/test_graphs.py
prov/tests/test_json.py
prov/tests/test_model.py
prov/tests/test_rdf.py
prov/tests/test_xml.py
prov/tests/utility.py
prov/tests/json/activity1.json
prov/tests/json/activity2.json
prov/tests/json/activity3.json
prov/tests/json/activity4.json
prov/tests/json/activity5.json
prov/tests/json/activity6.json
prov/tests/json/activity7.json
prov/tests/json/activity8.json
prov/tests/json/activity9.json
prov/tests/json/agent1.json
prov/tests/json/agent2.json
prov/tests/json/agent3.json
prov/tests/json/agent4.json
prov/tests/json/agent5.json
prov/tests/json/agent6.json
prov/tests/json/agent7.json
prov/tests/json/agent8.json
prov/tests/json/alternate1.json
prov/tests/json/association1.json
prov/tests/json/association2.json
prov/tests/json/association3.json
prov/tests/json/association4.json
prov/tests/json/association5.json
prov/tests/json/association6.json
prov/tests/json/association7.json
prov/tests/json/association8.json
prov/tests/json/association9.json
prov/tests/json/attr_activity0.json
prov/tests/json/attr_agent0.json
prov/tests/json/attr_association0.json
prov/tests/json/attr_association_one_role_attr0.json
prov/tests/json/attr_association_one_role_attr1.json
prov/tests/json/attr_association_one_role_attr10.json
prov/tests/json/attr_association_one_role_attr11.json
prov/tests/json/attr_association_one_role_attr12.json
prov/tests/json/attr_association_one_role_attr13.json
prov/tests/json/attr_association_one_role_attr14.json
prov/tests/json/attr_association_one_role_attr15.json
prov/tests/json/attr_association_one_role_attr16.json
prov-2.0.1.dist-info/AUTHORS.rst
prov-2.0.1.dist-info/LICENSE
prov-2.0.1.dist-info/METADATA
prov-2.0.1.dist-info/WHEEL
prov-2.0.1.dist-info/top_level.txt
prov-2.0.1.dist-info/RECORD
