Metadata-Version: 2.1
Name: prov
Version: 2.0.1
Summary: A library for W3C Provenance Data Model supporting PROV-JSON, PROV-XML and PROV-O (RDF)
Home-page: https://github.com/trungdong/prov
Author: Trung Dong Huynh
Author-email: trungdong@donggiang.com
License: MIT
Project-URL: Bug Reports, https://github.com/trungdong/prov/issues
Project-URL: Source, https://github.com/trungdong/prov
Keywords: provenance,graph,model,PROV,PROV-DM,PROV-JSON,W3C,PROV-XML,PROV-N,PROV-O,RDF
Classifier: Development Status :: 4 - Beta
Classifier: Intended Audience :: Developers
Classifier: Intended Audience :: Information Technology
Classifier: License :: OSI Approved :: MIT License
Classifier: Natural Language :: English
Classifier: Operating System :: OS Independent
Classifier: Programming Language :: Python :: 3
Classifier: Programming Language :: Python :: 3.8
Classifier: Programming Language :: Python :: 3.9
Classifier: Programming Language :: Python :: 3.10
Classifier: Programming Language :: Python :: 3.11
Classifier: Programming Language :: Python :: 3.12
Classifier: Programming Language :: Python :: 3 :: Only
Classifier: Programming Language :: Python :: Implementation :: CPython
Classifier: Programming Language :: Python :: Implementation :: PyPy
Classifier: Topic :: Scientific/Engineering :: Information Analysis
Classifier: Topic :: Security
Classifier: Topic :: System :: Logging
Requires-Python: >=3.6, <4
License-File: LICENSE
License-File: AUTHORS.rst
Requires-Dist: python-dateutil>=2.2
Requires-Dist: networkx>=2.0
Requires-Dist: lxml>=3.3.5
Requires-Dist: rdflib<7,>=4.2.1
Provides-Extra: dot
Requires-Dist: pydot>=1.2.0; extra == "dot"
